paystackease/__init__.py
paystackease/apaystack.py
paystackease/apis/__init__.py
paystackease/apis/async_apis/__init__.py
paystackease/apis/async_apis/aapple_pay.py
paystackease/apis/async_apis/abulk_charges.py
paystackease/apis/async_apis/acharges.py
paystackease/apis/async_apis/acustomers.py
paystackease/apis/async_apis/adedicated_virtual_accounts.py
paystackease/apis/async_apis/adisputes.py
paystackease/apis/async_apis/aintegration.py
paystackease/apis/async_apis/amiscellaneous.py
paystackease/apis/async_apis/apayment_pages.py
paystackease/apis/async_apis/apayment_requests.py
paystackease/apis/async_apis/aplans.py
paystackease/apis/async_apis/aproducts.py
paystackease/apis/async_apis/arefund.py
paystackease/apis/async_apis/asettlements.py
paystackease/apis/async_apis/asubaccounts.py
paystackease/apis/async_apis/asubscriptions.py
paystackease/apis/async_apis/aterminal.py
paystackease/apis/async_apis/atransaction_splits.py
paystackease/apis/async_apis/atransactions.py
paystackease/apis/async_apis/atransfer_recipients.py
paystackease/apis/async_apis/atransfers.py
paystackease/apis/async_apis/atransfers_control.py
paystackease/apis/async_apis/averification.py
paystackease/apis/sync_apis/__init__.py
paystackease/apis/sync_apis/apple_pay.py
paystackease/apis/sync_apis/bulk_charges.py
paystackease/apis/sync_apis/charges.py
paystackease/apis/sync_apis/customers.py
paystackease/apis/sync_apis/dedicated_virtual_accounts.py
paystackease/apis/sync_apis/disputes.py
paystackease/apis/sync_apis/integration.py
paystackease/apis/sync_apis/miscellaneous.py
paystackease/apis/sync_apis/payment_pages.py
paystackease/apis/sync_apis/payment_requests.py
paystackease/apis/sync_apis/plans.py
paystackease/apis/sync_apis/products.py
paystackease/apis/sync_apis/refund.py
paystackease/apis/sync_apis/settlements.py
paystackease/apis/sync_apis/subaccounts.py
paystackease/apis/sync_apis/subscriptions.py
paystackease/apis/sync_apis/terminal.py
paystackease/apis/sync_apis/transaction_splits.py
paystackease-2.2.0.dist-info/LICENSE
paystackease-2.2.0.dist-info/METADATA
paystackease-2.2.0.dist-info/WHEEL
paystackease-2.2.0.dist-info/RECORD
