Metadata-Version: 2.1
Name: paystackease
Version: 2.2.0
Summary: This is a simple api wrapper that implements both asynchronous and synchronous http requests to interact with Paystack APIs.
License: MIT
Keywords: paystack,paystackease,python,api,payment integration
Author: Peter Mbachu
Author-email: doublep098@gmail.com
Requires-Python: >=3.9,<4.0
Classifier: Development Status :: 5 - Production/Stable
Classifier: Intended Audience :: Developers
Classifier: License :: OSI Approved :: MIT License
Classifier: Natural Language :: English
Classifier: Operating System :: OS Independent
Classifier: Programming Language :: Python :: 3
Classifier: Programming Language :: Python :: 3.9
Classifier: Programming Language :: Python :: 3.10
Classifier: Programming Language :: Python :: 3.11
Classifier: Programming Language :: Python :: 3.12
Classifier: Topic :: Software Development :: Libraries :: Python Modules
Requires-Dist: aiohttp (>=3.8,<4.0)
Requires-Dist: python-decouple (>=3.8,<4.0)
Requires-Dist: requests (>=2.31,<3.0)
Project-URL: Bug Tracker, https://github.com/cla-bit/PayStackEase/issues
Project-URL: Documentation, https://paystackease.readthedocs.io/en/latest/
Project-URL: Homepage, https://github.com/cla-bit/PayStackEase
Project-URL: Source Code, https://github.com/cla-bit/PayStackEase
